jo3mnist/__init__.py
jo3mnist/__main__.py
jo3mnist/data.py
jo3mnist/equinox.py
jo3mnist/imagenet.py
jo3mnist/tiny_imagenet.py
jo3mnist/vis.py
jo3mnist-0.0.5.dist-info/LICENSE
jo3mnist-0.0.5.dist-info/METADATA
jo3mnist-0.0.5.dist-info/WHEEL
jo3mnist-0.0.5.dist-info/top_level.txt
jo3mnist-0.0.5.dist-info/RECORD
